rhodent/__init__.py
rhodent/dos.py
rhodent/perturbation.py
rhodent/spectrum.py
rhodent/typing.py
rhodent/voronoi.py
rhodent/calculators/__init__.py
rhodent/calculators/base.py
rhodent/calculators/density.py
rhodent/calculators/dipole.py
rhodent/calculators/energy.py
rhodent/calculators/hotcarriers.py
rhodent/density_matrices/__init__.py
rhodent/density_matrices/base.py
rhodent/density_matrices/buffer.py
rhodent/density_matrices/density_matrix.py
rhodent/density_matrices/frequency.py
rhodent/density_matrices/time.py
rhodent/density_matrices/distributed/__init__.py
rhodent/density_matrices/distributed/base.py
rhodent/density_matrices/distributed/frequency.py
rhodent/density_matrices/distributed/pulse.py
rhodent/density_matrices/distributed/time.py
rhodent/density_matrices/readers/__init__.py
rhodent/density_matrices/readers/gpaw.py
rhodent/density_matrices/readers/numpy.py
rhodent/response/__init__.py
rhodent/response/base.py
rhodent/response/gpaw.py
rhodent/response/numpy.py
rhodent/utils/__init__.py
rhodent/utils/env.py
rhodent/utils/logging.py
rhodent/utils/memory.py
rhodent/utils/result.py
rhodent/writers/__init__.py
rhodent/writers/density.py
rhodent/writers/dos.py
rhodent/writers/energy.py
rhodent/writers/hcdist.py
rhodent/writers/spectrum.py
rhodent/writers/tcm.py
rhodent/writers/writer.py
rhodent-1.0.dist-info/licenses/LICENSE
rhodent-1.0.dist-info/METADATA
rhodent-1.0.dist-info/WHEEL
rhodent-1.0.dist-info/top_level.txt
rhodent-1.0.dist-info/RECORD
