Metadata-Version: 2.4
Name: rhodent
Version: 1.0
Summary: Analyzing hot-carrier distributions from TD-DFT simulations
Author: The rhodent developer team
Maintainer: The rhodent developer team
License-Expression: MPL-2.0
Project-URL: Documentation, https://rhodent.materialsmodeling.org
Project-URL: Repository, https://gitlab.com/materials-modeling/rhodent/
Keywords: chemistry,physics,scientific
Classifier: Development Status :: 5 - Production/Stable
Classifier: Operating System :: OS Independent
Classifier: Programming Language :: Python :: 3 :: Only
Classifier: Programming Language :: Python :: 3
Classifier: Programming Language :: Python :: 3.9
Classifier: Programming Language :: Python :: 3.10
Classifier: Programming Language :: Python :: 3.11
Classifier: Programming Language :: Python :: 3.12
Classifier: Programming Language :: Python :: 3.13
Classifier: Intended Audience :: Education
Classifier: Intended Audience :: Science/Research
Classifier: Programming Language :: Python
Classifier: Topic :: Scientific/Engineering :: Chemistry
Classifier: Topic :: Scientific/Engineering :: Physics
Requires-Python: >=3.9
License-File: LICENSE
Requires-Dist: ase
Requires-Dist: gpaw
Requires-Dist: numpy
Dynamic: license-file
